llamator/__init__.py
llamator/__version__.py
llamator/initial_validation.py
llamator/logging.py
llamator/main.py
llamator/py.typed
llamator/attack_data/__init__.py
llamator/attack_data/base64_prompts.parquet
llamator/attack_data/deceptive_delight.parquet
llamator/attack_data/ethical_compliance.parquet
llamator/attack_data/harmbench_text.parquet
llamator/attack_data/suffixes.parquet
llamator/attack_data/system_prompt_leakage.parquet
llamator/attack_data/ucar-dan_prompts.parquet
llamator/attack_data/vlm_m_attack_prepared.parquet
llamator/attack_data/vlm_m_attack/__init__.py
llamator/attack_data/vlm_m_attack/data_download.py
llamator/attack_provider/__init__.py
llamator/attack_provider/attack_loader.py
llamator/attack_provider/attack_registry.py
llamator/attack_provider/image_utils.py
llamator/attack_provider/run_tests.py
llamator/attack_provider/test_base.py
llamator/attack_provider/util.py
llamator/attack_provider/work_progress_pool.py
llamator/attacks/__init__.py
llamator/attacks/aim.py
llamator/attacks/autodan_turbo.py
llamator/attacks/base64_injection.py
llamator/attacks/bon.py
llamator/attacks/cop.py
llamator/attacks/crecsendo.py
llamator/attacks/dan.py
llamator/attacks/deceptive_delight.py
llamator/attacks/dialogue_injection_continuation.py
llamator/attacks/dialogue_injection_devmode.py
llamator/attacks/ethical_compliance.py
llamator/attacks/harmbench.py
llamator/attacks/linguistic.py
llamator/attacks/linguistic_sandwich.py
llamator/attacks/logical_inconsistencies.py
llamator/attacks/pair.py
llamator/attacks/repetition_token.py
llamator/attacks/semantic_game.py
llamator/attacks/shuffle.py
llamator/attacks/suffix.py
llamator/attacks/sycophancy.py
llamator/attacks/system_prompt_leakage.py
llamator/attacks/time_machine.py
llamator/attacks/ucar.py
llamator/attacks/vlm_lowres_docs.py
llamator/attacks/vlm_m_attack.py
llamator/attacks/vlm_text_hallucination.py
llamator/client/__init__.py
llamator/client/attack_config.py
llamator/client/chat_client.py
llamator-3.5.0.dist-info/licenses/LICENSE.md
llamator-3.5.0.dist-info/METADATA
llamator-3.5.0.dist-info/WHEEL
llamator-3.5.0.dist-info/top_level.txt
llamator-3.5.0.dist-info/RECORD
