Metadata-Version: 2.4
Name: llamator
Version: 3.5.0
Summary: Framework for testing vulnerabilities of GenAI systems.
Home-page: https://github.com/LLAMATOR-Core/llamator
Author: Roman Neronov, Timur Nizamov, Nikita Ivanov
License: Attribution 4.0 International
Project-URL: Documentation, https://llamator-core.github.io/llamator
Classifier: Development Status :: 5 - Production/Stable
Classifier: Environment :: Console
Classifier: Intended Audience :: Science/Research
Classifier: License :: Other/Proprietary License
Classifier: Natural Language :: English
Classifier: Operating System :: OS Independent
Classifier: Programming Language :: Python :: 3.9
Classifier: Programming Language :: Python :: 3.10
Classifier: Programming Language :: Python :: 3.11
Classifier: Topic :: Scientific/Engineering :: Artificial Intelligence
Classifier: Topic :: Scientific/Engineering :: Information Analysis
Classifier: Topic :: Security
Classifier: Topic :: Software Development :: Testing
Requires-Python: >=3.9
License-File: LICENSE.md
Requires-Dist: python-dotenv>=0.5.1
Requires-Dist: httpx==0.27.2
Requires-Dist: openai==1.68.2
Requires-Dist: langchain==0.3.21
Requires-Dist: langchain-community==0.3.20
Requires-Dist: langchain-core==0.3.49
Requires-Dist: tqdm==4.66.3
Requires-Dist: colorama==0.4.6
Requires-Dist: prettytable==3.10.0
Requires-Dist: pandas==2.2.2
Requires-Dist: inquirer==3.2.4
Requires-Dist: prompt-toolkit==3.0.43
Requires-Dist: openpyxl==3.1.5
Requires-Dist: python-docx==1.1.2
Requires-Dist: datetime==5.5
Requires-Dist: pyarrow==19.0.1
Requires-Dist: pymupdf==1.25.5
Requires-Dist: pillow==11.1.0
Requires-Dist: huggingface_hub==0.30.1
Requires-Dist: datasets==3.5.0
Requires-Dist: GitPython==3.1.44
Dynamic: license-file
